umami_asgi/__init__.py
umami_asgi/middleware.py
umami_asgi/middleware_test.py
umami_asgi/umami_api.py
umami_asgi-0.2.0.dist-info/METADATA
umami_asgi-0.2.0.dist-info/WHEEL
umami_asgi-0.2.0.dist-info/licenses/LICENSE
umami_asgi-0.2.0.dist-info/RECORD
