Metadata-Version: 2.3
Name: umami-asgi
Version: 0.2.0
Summary: A middleware for your ASGI application that enables Umami analytics.
Project-URL: Homepage, https://github.com/Tanikai/umami-asgi-middleware
Project-URL: Issues, https://github.com/Tanikai/umami-asgi-middleware/issues
Author-email: Kai Anter <kai@anter.dev>
License-Expression: MIT
License-File: LICENSE
Keywords: analytics,asgi,asgi-middleware,metrics,middleware
Classifier: License :: OSI Approved :: MIT License
Classifier: Operating System :: OS Independent
Classifier: Programming Language :: Python :: 3
Requires-Python: >=3.8
